protein_information_system/__init__.py
protein_information_system/config/config.yaml
protein_information_system/config/constants.yaml
protein_information_system/helpers/__init__.py
protein_information_system/helpers/clustering/cdhit.py
protein_information_system/helpers/config/__init__.py
protein_information_system/helpers/config/yaml.py
protein_information_system/helpers/layers.py
protein_information_system/helpers/logger/__init__.py
protein_information_system/helpers/logger/logger.py
protein_information_system/helpers/parser/__init__.py
protein_information_system/helpers/parser/parser.py
protein_information_system/helpers/services/services.py
protein_information_system/main.py
protein_information_system/operation/__init__.py
protein_information_system/operation/embedding/__init__.py
protein_information_system/operation/embedding/proccess/__init__.py
protein_information_system/operation/embedding/proccess/sequence/__init__.py
protein_information_system/operation/embedding/proccess/sequence/ankh3.py
protein_information_system/operation/embedding/proccess/sequence/esm.py
protein_information_system/operation/embedding/proccess/sequence/esm3c.py
protein_information_system/operation/embedding/proccess/sequence/t5.py
protein_information_system/operation/embedding/proccess/structure/3di.py
protein_information_system/operation/embedding/proccess/structure/__init__.py
protein_information_system/operation/embedding/sequence_embedding.py
protein_information_system/operation/embedding/structure_3di.py
protein_information_system/operation/extraction/__init__.py
protein_information_system/operation/extraction/accessions.py
protein_information_system/operation/extraction/pdb.py
protein_information_system/operation/extraction/protein_annotations_file.py
protein_information_system/operation/extraction/results.csv
protein_information_system/operation/extraction/uniprot.py
protein_information_system/sql/__init__.py
protein_information_system/sql/base/database_manager.py
protein_information_system-3.0.0.dist-info/METADATA
protein_information_system-3.0.0.dist-info/WHEEL
protein_information_system-3.0.0.dist-info/entry_points.txt
protein_information_system-3.0.0.dist-info/RECORD
