Metadata-Version: 2.3
Name: protein_information_system
Version: 3.0.0
Summary: Comprehensive Python Module for Protein Data Management: Designed for streamlined integration and processing of protein information from both UniProt and PDB. Equipped with features for concurrent data fetching, robust error handling, and database synchronization.
Author: frapercan
Author-email: frapercan1@alum.us.es
Requires-Python: >=3.10,<4.0
Classifier: Programming Language :: Python :: 3
Classifier: Programming Language :: Python :: 3.10
Classifier: Programming Language :: Python :: 3.11
Classifier: Programming Language :: Python :: 3.12
Classifier: Programming Language :: Python :: 3.13
Requires-Dist: bio (>=1.8.0,<2.0.0)
Requires-Dist: esm (>=3.2.1,<4.0.0)
Requires-Dist: gemmi (>=0.7.3,<0.8.0)
Requires-Dist: h5py (>=3.12.1,<4.0.0)
Requires-Dist: mini3di (>=0.2.1,<0.3.0)
Requires-Dist: pandas (>=2.3.1,<3.0.0)
Requires-Dist: pgvector (>=0.4,<0.5)
Requires-Dist: pika (>=1.3.2,<2.0.0)
Requires-Dist: psycopg2-binary (>=2.9.9,<3.0.0)
Requires-Dist: pyyaml (>=6.0.1,<7.0.0)
Requires-Dist: retry (>=0.9.2,<0.10.0)
Requires-Dist: sentencepiece (>=0.2.0,<0.3.0)
Requires-Dist: sqlalchemy (>=2.0.40,<3.0.0)
Requires-Dist: tokenizer (>=3.4.3,<4.0.0)
Requires-Dist: torch (>=2.3.0,<3.0.0)
Requires-Dist: transformers (>=4.48.1,<5.0.0)
